mcp_k8s_server/__init__.py
mcp_k8s_server/config.py
mcp_k8s_server/main.py
mcp_k8s_server/server.py
mcp_k8s_server/k8s/__init__.py
mcp_k8s_server/k8s/client.py
mcp_k8s_server/k8s/monitoring.py
mcp_k8s_server/k8s/operations.py
mcp_k8s_server/prompts/__init__.py
mcp_k8s_server/prompts/analysis_prompts.py
mcp_k8s_server/resources/__init__.py
mcp_k8s_server/resources/cluster_resources.py
mcp_k8s_server/tools/__init__.py
mcp_k8s_server/tools/monitoring_tools.py
mcp_k8s_server/tools/operation_tools.py
mcp_k8s_server/tools/resource_tools.py
mcp_k8s_server-0.1.2.dist-info/licenses/LICENSE
mcp_k8s_server-0.1.2.dist-info/METADATA
mcp_k8s_server-0.1.2.dist-info/WHEEL
mcp_k8s_server-0.1.2.dist-info/entry_points.txt
mcp_k8s_server-0.1.2.dist-info/top_level.txt
mcp_k8s_server-0.1.2.dist-info/RECORD
