Metadata-Version: 2.4
Name: mcp-k8s-server
Version: 0.1.2
Summary: Kubernetes management MCP server
Author: Lewis Guo
Author-email: Lewis Guo <guolisen@gmail.com>
License: MIT
Project-URL: Homepage, https://github.com/guolisen/mcp_k8s_server
Requires-Python: >=3.13
License-File: LICENSE
Requires-Dist: mcp>=1.6.0
Requires-Dist: kubernetes>=30.0.0
Requires-Dist: pyyaml>=6.0.1
Requires-Dist: httpx>=0.28.1
Requires-Dist: click>=8.1.8
Requires-Dist: pydantic>=2.11.1
Requires-Dist: pydantic-settings>=2.8.1
Requires-Dist: pip>=25.0.1
Requires-Dist: debugpy>=1.8.13
Requires-Dist: setuptools>=78.1.0
Requires-Dist: wheel>=0.45.1
Requires-Dist: twine>=6.1.0
Requires-Dist: pkginfo>=1.12.1.2
Requires-Dist: urllib3>=2.3.0
Requires-Dist: requests-toolbelt>=1.0.0
Requires-Dist: build>=1.2.2.post1
Dynamic: license-file
Dynamic: requires-python
